EDAPro/__init__.py
EDAPro/module.py
data_sage-0.1.dist-info/licenses/LICENSE
data_sage-0.1.dist-info/METADATA
data_sage-0.1.dist-info/WHEEL
data_sage-0.1.dist-info/top_level.txt
data_sage-0.1.dist-info/RECORD
